odoo/addons/report_fillpdf/README.rst
odoo/addons/report_fillpdf/__init__.py
odoo/addons/report_fillpdf/__manifest__.py
odoo/addons/report_fillpdf/controllers/__init__.py
odoo/addons/report_fillpdf/controllers/main.py
odoo/addons/report_fillpdf/demo/report.xml
odoo/addons/report_fillpdf/i18n/de.po
odoo/addons/report_fillpdf/i18n/fr.po
odoo/addons/report_fillpdf/models/__init__.py
odoo/addons/report_fillpdf/models/ir_report.py
odoo/addons/report_fillpdf/report/__init__.py
odoo/addons/report_fillpdf/report/report_fill_pdf.py
odoo/addons/report_fillpdf/report/report_partner_pdf.py
odoo/addons/report_fillpdf/static/description/icon.png
odoo/addons/report_fillpdf/static/src/js/report/qwebactionmanager.js
odoo/addons/report_fillpdf/static/src/pdf/partner_pdf.pdf
odoo/addons/report_fillpdf/tests/__init__.py
odoo/addons/report_fillpdf/tests/test_report.py
odoo/addons/report_fillpdf/views/webclient_templates.xml
odoo11_addon_report_fillpdf-11.0.1.0.1.dist-info/DESCRIPTION.rst
odoo11_addon_report_fillpdf-11.0.1.0.1.dist-info/METADATA
odoo11_addon_report_fillpdf-11.0.1.0.1.dist-info/RECORD
odoo11_addon_report_fillpdf-11.0.1.0.1.dist-info/WHEEL
odoo11_addon_report_fillpdf-11.0.1.0.1.dist-info/metadata.json
odoo11_addon_report_fillpdf-11.0.1.0.1.dist-info/top_level.txt
